everyai_filefinder/__init__.py
everyai_filefinder/cli.py
everyai_filefinder/finder.py
everyai_filefinder-1.0.0.dist-info/LICENSE
everyai_filefinder-1.0.0.dist-info/METADATA
everyai_filefinder-1.0.0.dist-info/WHEEL
everyai_filefinder-1.0.0.dist-info/entry_points.txt
everyai_filefinder-1.0.0.dist-info/top_level.txt
everyai_filefinder-1.0.0.dist-info/RECORD
