Metadata-Version: 2.2
Name: everyai_filefinder
Version: 1.0.0
Summary: A CLI tool for searching, filtering, and managing files.
Home-page: https://github.com/yourusername/filefinder
Author: Your Name
Author-email: Frank Mashraqi <softwareengineer99@yahoo.com>
License: MIT
Project-URL: Homepage, https://github.com/everyai/everyai_filefinder
Project-URL: Repository, https://github.com/everyai/everyai_filefinder
Requires-Python: >=3.7
License-File: LICENSE
Requires-Dist: rich
Dynamic: author
Dynamic: home-page
Dynamic: requires-python
